duckdb_provider/__init__.py
duckdb_provider/hooks/__init__.py
duckdb_provider/hooks/duckdb_hook.py
airflow_provider_duckdb-0.2.0.dist-info/LICENSE
airflow_provider_duckdb-0.2.0.dist-info/METADATA
airflow_provider_duckdb-0.2.0.dist-info/WHEEL
airflow_provider_duckdb-0.2.0.dist-info/entry_points.txt
airflow_provider_duckdb-0.2.0.dist-info/top_level.txt
airflow_provider_duckdb-0.2.0.dist-info/RECORD
