Metadata-Version: 2.1
Name: airflow-provider-duckdb
Version: 0.2.0
Summary: DuckDB (duckdb.org) provider for Apache Airflow
Home-page: http://astronomer.io/
Author: Julian LaNeve
Author-email: julian@astronomer.io
License: Apache License 2.0
Classifier: Framework :: Apache Airflow
Classifier: Framework :: Apache Airflow :: Provider
Requires-Python: ~=3.7
License-File: LICENSE
